vnlunar/__init__.py
vnlunar/astrology.py
vnlunar/calendar.py
vnlunar/constants.py
vnlunar/core.py
vnlunar/direction.py
vnlunar/lunar_types.py
vnlunar-1.0.3.dist-info/licenses/LICENSE
vnlunar-1.0.3.dist-info/METADATA
vnlunar-1.0.3.dist-info/WHEEL
vnlunar-1.0.3.dist-info/top_level.txt
vnlunar-1.0.3.dist-info/RECORD
